<object clone="/base/obj/thing" owner="roccon">
  <Base:Thing>
    <Ur:UrObject/>
    <Base:Bulk immobile="false" mass="1" density="1"/>
    <Base:Container flexible="false" transparent-container="false" public-container="false" tight="false" capacity="0" maxweight="0"/>
    <Base:Misc gender="neuter" volition="false" weapon="false" default_stance="standing" combinable="false" discrete="false" by_weight="false" tight="false" scriptrunner="false">
      <Base:Edible value="false"/>
      <Base:Potable value="false"/>
      <Base:DrinkMessageFirst></Base:DrinkMessageFirst>
      <Base:DrinkMessageThird></Base:DrinkMessageThird>
      <Base:Transparency value="false"/>
      <Base:Unsafe value="false"/>
      <Base:Safe value="false"/>
      <Base:ClothesExpected value="false"/>
      <Base:DieMessageFirst></Base:DieMessageFirst>
      <Base:DieMessageThird></Base:DieMessageThird>
    </Base:Misc>
    <Base:Details>
      <Base:Detail id="default" prime="true" def="false" abstract="false" hidden="false" luminosity="0" targetable_in_dark="false" plural="false">
        <Base:Preposition close="true" against="false" under="false" on="false" inside="false" near="true" over="false" behind="false" before="true" beside="true"/>
        <Base:Names>
          <Base:SNames>
            <Base:SName sname="stand"/>
            <Base:SName sname="arrowstand"/>
            <Base:SName sname="arrow-stand"/>
          </Base:SNames>
          <Base:PNames>
            <Base:PName pname="stands"/>
            <Base:PName pname="arrowstands"/>
            <Base:PName pname="arrow-stands"/>
          </Base:PNames>
        </Base:Names>
        <Base:Adjectives>
          <Base:Adjective adjective="bow"/>
        </Base:Adjectives>
        <Base:Descriptions>
          <Base:Description type="brief">
             arrow stand
          </Base:Description>
          <Base:Description type="look">
             A hip-length wooden box, standing against the wall. A dozen quivers with arrows hang from it.
          </Base:Description>
        </Base:Descriptions>
        <Base:Exit door="false" never_obvious="false" obvious_when_open="false" hidden_when_closed="false" separate="false" self-locking="false" deadbolt="false"/>
        <Base:Climbable/>
      </Base:Detail>
      <Base:Detail id="arrows" prime="false" def="true" abstract="false" hidden="false" luminosity="0" targetable_in_dark="false" plural="true">
        <Base:Preposition close="false" against="false" under="false" on="false" inside="false" near="false" over="false" behind="false" before="false" beside="false"/>
        <Base:Names>
          <Base:SNames>
            <Base:SName sname="arrow"/>
          </Base:SNames>
          <Base:PNames>
            <Base:PName pname="arrows"/>
          </Base:PNames>
        </Base:Names>
        <Base:Adjectives/>
        <Base:Descriptions>
          <Base:Description type="brief">
             a stack of arrows
          </Base:Description>
          <Base:Description type="look">
             Some arrows in a quiver. Only their tails are visible, which are covered with white feathers.
          </Base:Description>
        </Base:Descriptions>
        <Base:Exit door="false" never_obvious="false" obvious_when_open="false" hidden_when_closed="false" separate="false" self-locking="false" deadbolt="false"/>
        <Base:Climbable/>
      </Base:Detail>
      <Base:Detail id="quivers" prime="false" def="true" abstract="false" hidden="false" luminosity="0" targetable_in_dark="false" plural="true">
        <Base:Preposition close="false" against="false" under="false" on="false" inside="false" near="false" over="false" behind="false" before="false" beside="false"/>
        <Base:Names>
          <Base:SNames>
            <Base:SName sname="quiver"/>
          </Base:SNames>
          <Base:PNames>
            <Base:PName pname="quivers"/>
          </Base:PNames>
        </Base:Names>
        <Base:Adjectives/>
        <Base:Descriptions>
          <Base:Description type="brief">quivers</Base:Description>
          <Base:Description type="look">
             Some cylindrical quivers, hanging from the rack with their strap. Their colors are mostly dark. Each contains a stack of arrows.
          </Base:Description>
        </Base:Descriptions>
        <Base:Exit door="false" never_obvious="false" obvious_when_open="false" hidden_when_closed="false" separate="false" self-locking="false" deadbolt="false"/>
        <Base:Climbable/>
      </Base:Detail>
    </Base:Details>
    <Base:Combat>
      <Base:Strength value="1"/>
      <Base:MaxFatigue value="1"/>
    </Base:Combat>
    <Base:Clothing>
      <Base:SingleWear value="false"/>
    </Base:Clothing>
    <Base:Crafting see_level="0" do_level="0" time="0" attention="false" held="false">
      <Base:Ingredients/>
      <Base:Tools/>
      <Base:CraftVerbs/>
    </Base:Crafting>
    <Base:InitialContents/>
    <Base:InitialProperties/>
    <Core:Properties>
      <Core:Property property="revisions">
         (\{ 1107209474, "zwoc", "E", 1128523675, "roccon", "E", 1128523693, "roccon", "E", 1128523774, "roccon", "E", 1128523795, "roccon", "E", 1128523811, "roccon", "E", 1128524225, "roccon", "E", 1128525624, "roccon", "E", 1128525658, "roccon", "E", 1128525934, "roccon", "E", 1128526259, "roccon", "E", 1128526550, "roccon", "E", 1128968047, "roccon", "E", 1128968090, "roccon", "E", 1128968140, "roccon", "E", 1128968297, "roccon", "E", 1128968493, "roccon", "E", 1128968508, "roccon", "E", 1128968622, "roccon", "E", 1128968740, "roccon", "E", 1129155212, "roccon", "E", 1307225918, "tunk_bodin", "R", 1570808526, "sendnoodlez", "R" \})
      </Core:Property>
      <Core:Property property="skill:fatigue">1.0</Core:Property>
      <Core:Property property="volition">0</Core:Property>
    </Core:Properties>
    <Notes:Notes/>
  </Base:Thing>
</object>
