<object clone="/base/obj/thing" owner="tunk_bodin">
  <Base:Thing>
    <Ur:UrObject/>
    <Base:Bulk immobile="false" mass="0.5" density="1"/>
    <Base:Container flexible="true" transparent-container="false" public-container="false" tight="true" capacity="0.5" maxweight="25" verb2="contain" verb3="contains"/>
    <Base:Misc gender="neuter" volition="false" weapon="false" default_stance="none" combinable="false" discrete="false" by_weight="false" tight="true" scriptrunner="false">
      <Base:Edible value="false"/>
      <Base:Potable value="false"/>
      <Base:DrinkMessageFirst></Base:DrinkMessageFirst>
      <Base:DrinkMessageThird></Base:DrinkMessageThird>
      <Base:Transparency value="false"/>
      <Base:Unsafe value="false"/>
      <Base:Safe value="false"/>
      <Base:ClothesExpected value="false"/>
      <Base:DieMessageFirst></Base:DieMessageFirst>
      <Base:DieMessageThird></Base:DieMessageThird>
    </Base:Misc>
    <Base:Details>
      <Base:Detail id="default" prime="true" def="false" abstract="false" hidden="false" luminosity="0" targetable_in_dark="false" plural="false">
        <Base:Preposition close="true" against="true" under="false" on="true" inside="true" near="true" over="true" behind="false" before="false" beside="true"/>
        <Base:Names>
          <Base:SNames>
            <Base:SName sname="hole"/>
          </Base:SNames>
          <Base:PNames>
            <Base:PName pname="holes"/>
          </Base:PNames>
        </Base:Names>
        <Base:Adjectives>
          <Base:Adjective adjective="burrowed"/>
          <Base:Adjective adjective="dirt"/>
          <Base:Adjective adjective="small"/>
        </Base:Adjectives>
        <Base:Descriptions>
          <Base:Description type="brief">
             small hole
          </Base:Description>
          <Base:Description type="examine">
             A small dirt hole has been burrowed in the southeastern corner of this room.
          </Base:Description>
          <Base:Description type="glance">
             A small hole.
          </Base:Description>
          <Base:Description type="look">
             A small dirt hole has been burrowed here.
          </Base:Description>
        </Base:Descriptions>
        <Base:Exit door="false" never_obvious="false" obvious_when_open="false" hidden_when_closed="false" separate="false" self-locking="false" deadbolt="false"/>
        <Base:Climbable/>
      </Base:Detail>
    </Base:Details>
    <Base:Combat>
      <Base:Strength value="1"/>
      <Base:MaxFatigue value="1"/>
    </Base:Combat>
    <Base:Clothing>
      <Base:SingleWear value="false"/>
    </Base:Clothing>
    <Base:Crafting see_level="0" do_level="0" time="0" attention="false" held="false">
      <Base:Ingredients/>
      <Base:Tools/>
      <Base:CraftVerbs/>
    </Base:Crafting>
    <Base:InitialContents/>
    <Base:InitialProperties/>
    <Core:Properties>
      <Core:Property property="misc:lastdropped">
         "1100465944 Manny[tunk_bodin]"
      </Core:Property>
      <Core:Property property="revisions">
         (\{ 1096500807, "tunk_bodin", "X", 1096501098, "tunk_bodin", "X", 1096507487, "tunk_bodin", "X", 1097728692, "tunk_bodin", "X", 1097730041, "tunk_bodin", "X", 1097730187, "tunk_bodin", "X", 1097730678, "tunk_bodin", "X", 1099957222, "tunk_bodin", "X", 1100236089, "tunk_bodin", "X", 1127063366, "tunk_bodin", "X", 1127063808, "tunk_bodin", "E", 1307223567, "tunk_bodin", "R", 1307223803, "tunk_bodin", "R", 1571156946, "sendnoodlez", "R" \})
      </Core:Property>
      <Core:Property property="skill:fatigue">1.0</Core:Property>
      <Core:Property property="volition">0</Core:Property>
    </Core:Properties>
    <Notes:Notes/>
  </Base:Thing>
</object>
