<object clone="/base/obj/thing" owner="slurpeeslurp">
  <Base:Thing>
    <Ur:UrObject/>
    <Base:Bulk immobile="false" mass="0.001" density="0.1"/>
    <Base:Container flexible="false" transparent-container="false" public-container="false" tight="false" capacity="0" maxweight="0"/>
    <Base:Misc gender="neuter" volition="false" weapon="false" default_stance="lying" combinable="false" discrete="false" by_weight="false" tight="false" scriptrunner="false">
      <Base:Edible value="false"/>
      <Base:Potable value="false"/>
      <Base:DrinkMessageFirst/>
      <Base:DrinkMessageThird/>
      <Base:Transparency value="false"/>
      <Base:Unsafe value="false"/>
      <Base:Safe value="false"/>
      <Base:ClothesExpected value="false"/>
      <Base:DieMessageFirst/>
      <Base:DieMessageThird/>
    </Base:Misc>
    <Base:Details>
      <Base:Detail id="objskin" prime="true" def="false" abstract="false" hidden="false" luminosity="0" targetable_in_dark="false" plural="false">
        <Base:Preposition close="false" against="false" under="false" on="false" inside="false" near="true" over="false" behind="false" before="false" beside="false"/>
        <Base:Names>
          <Base:SNames>
            <Base:SName sname="certificate"/>
            <Base:SName sname="grant"/>
          </Base:SNames>
          <Base:PNames>
            <Base:PName pname="grants"/>
            <Base:PName pname="certificates"/>
          </Base:PNames>
        </Base:Names>
        <Base:Adjectives>
          <Base:Adjective adjective="formal"/>
          <Base:Adjective adjective="grant"/>
          <Base:Adjective adjective="land"/>
          <Base:Adjective adjective="purple"/>
          <Base:Adjective adjective="tyrian"/>
        </Base:Adjectives>
        <Base:Descriptions>
          <Base:Description type="brief">
             tyrian purple land grant
          </Base:Description>
          <Base:Description type="examine">
             A tyrian purple land grant. This piece of parchment certifies that a gift of land or privileges has been given by an authority in the Rinaldi household as a reward for services to an individual of Nobility. Delicate writing has been inked upon its surface.
          </Base:Description>
          <Base:Description type="look">
             A tyrian purple land grant.
          </Base:Description>
          <Base:Description type="pbrief">
             tyrian purple land grants
          </Base:Description>
        </Base:Descriptions>
        <Base:Exit door="false" never_obvious="false" obvious_when_open="false" hidden_when_closed="false" separate="false" self-locking="false" deadbolt="false"/>
        <Base:Climbable/>
      </Base:Detail>
    </Base:Details>
    <Base:Combat>
      <Base:Strength value="10"/>
      <Base:MaxFatigue value="100"/>
    </Base:Combat>
    <Base:Clothing>
      <Base:SingleWear value="false"/>
    </Base:Clothing>
    <Base:Crafting see_level="0" do_level="0" time="0" attention="false" held="false">
      <Base:Ingredients/>
      <Base:Tools/>
      <Base:CraftVerbs/>
    </Base:Crafting>
    <Base:InitialContents/>
    <Base:InitialProperties>
      <Base:InitialProperty property="bilbo:inherit:react:chant">
         \<Generic:DB:ScrollDB\>
      </Base:InitialProperty>
      <Base:InitialProperty property="bilbo:inherit:react:cite">
         \<Generic:DB:ScrollDB\>
      </Base:InitialProperty>
      <Base:InitialProperty property="bilbo:inherit:react:instruct">
         \<Generic:DB:ScrollDB\>
      </Base:InitialProperty>
      <Base:InitialProperty property="bilbo:inherit:react:orate">
         \<Generic:DB:ScrollDB\>
      </Base:InitialProperty>
      <Base:InitialProperty property="bilbo:inherit:react:preach">
         \<Generic:DB:ScrollDB\>
      </Base:InitialProperty>
      <Base:InitialProperty property="bilbo:inherit:react:recite">
         \<Generic:DB:ScrollDB\>
      </Base:InitialProperty>
      <Base:InitialProperty property="bilbo:inherit:react:sing">
         \<Generic:DB:ScrollDB\>
      </Base:InitialProperty>
      <Base:InitialProperty property="bilbo:inherit:react:translate">
         \<Generic:DB:ScrollDB\>
      </Base:InitialProperty>
      <Base:InitialProperty property="writable">
         "1"
      </Base:InitialProperty>
    </Base:InitialProperties>
    <Core:Properties>
      <Core:Property property="bilbo:inherit:react:chant">
         \<Generic:DB:ScrollDB\>
      </Core:Property>
      <Core:Property property="bilbo:inherit:react:cite">
         \<Generic:DB:ScrollDB\>
      </Core:Property>
      <Core:Property property="bilbo:inherit:react:instruct">
         \<Generic:DB:ScrollDB\>
      </Core:Property>
      <Core:Property property="bilbo:inherit:react:orate">
         \<Generic:DB:ScrollDB\>
      </Core:Property>
      <Core:Property property="bilbo:inherit:react:preach">
         \<Generic:DB:ScrollDB\>
      </Core:Property>
      <Core:Property property="bilbo:inherit:react:recite">
         \<Generic:DB:ScrollDB\>
      </Core:Property>
      <Core:Property property="bilbo:inherit:react:sing">
         \<Generic:DB:ScrollDB\>
      </Core:Property>
      <Core:Property property="bilbo:inherit:react:translate">
         \<Generic:DB:ScrollDB\>
      </Core:Property>
      <Core:Property property="bilbo:solo:refresh">
         "run"
      </Core:Property>
      <Core:Property property="bilbo:solo:refresh:0010">
         "set this.scrollrefreshtemp to \$lookup(Generic:DB:ScrollDB)"
      </Core:Property>
      <Core:Property property="bilbo:solo:refresh:0020">
         "set this.bilbo:inherit:react:chant to this.scrollrefreshtemp"
      </Core:Property>
      <Core:Property property="bilbo:solo:refresh:0030">
         "set this.bilbo:inherit:react:cite to this.scrollrefreshtemp"
      </Core:Property>
      <Core:Property property="bilbo:solo:refresh:0040">
         "set this.bilbo:inherit:react:instruct to this.scrollrefreshtemp"
      </Core:Property>
      <Core:Property property="bilbo:solo:refresh:0050">
         "set this.bilbo:inherit:react:sing to this.scrollrefreshtemp"
      </Core:Property>
      <Core:Property property="bilbo:solo:refresh:0060">
         "set this.bilbo:inherit:react:orate to this.scrollrefreshtemp"
      </Core:Property>
      <Core:Property property="bilbo:solo:refresh:0070">
         "set this.bilbo:inherit:react:preach to this.scrollrefreshtemp"
      </Core:Property>
      <Core:Property property="bilbo:solo:refresh:0080">
         "set this.bilbo:inherit:react:recite to this.scrollrefreshtemp"
      </Core:Property>
      <Core:Property property="bilbo:solo:refresh:0090">
         "set this.bilbo:inherit:react:translate to nil"
      </Core:Property>
      <Core:Property property="bilbo:solo:refresh:0100">
         "set writable 1"
      </Core:Property>
      <Core:Property property="bilbo:solo:refresh:0110">
         "set this.scrollrefreshtemp to nil"
      </Core:Property>
      <Core:Property property="export:nip:item:cost">
         0
      </Core:Property>
      <Core:Property property="export:trait:trash">1</Core:Property>
      <Core:Property property="export:writable">
         "true"
      </Core:Property>
      <Core:Property property="misc:lastdopped">
         "1048692858 /usr/SkotOS/merry/fe76fdbb6793c3e6fedfa42659af22d0"
      </Core:Property>
      <Core:Property property="nip:item:cost">0</Core:Property>
      <Core:Property property="revisions">
         (\{ 1170617073, "necate", "E", 1172544909, "tonyd", "E", 1172544951, "tonyd", "E", 1172545016, "tonyd", "E", 1174582510, "tunk_bodin", "E", 1174582644, "tunk_bodin", "E", 1174582665, "tunk_bodin", "E", 1174583948, "tunk_bodin", "E", 1174584099, "tunk_bodin", "E", 1174584337, "tunk_bodin", "E", 1175593500, "necate", "E", 1175668147, "necate", "E", 1176609116, "necate", "E", 1213693116, "slurpeeslurp", "E", 1213693120, "slurpeeslurp", "E", 1213693136, "slurpeeslurp", "E", 1213693151, "slurpeeslurp", "E", 1213693162, "slurpeeslurp", "E", 1213693213, "slurpeeslurp", "E", 1213693732, "slurpeeslurp", "E", 1213693755, "slurpeeslurp", "E", 1213694099, "slurpeeslurp", "E", 1213694153, "slurpeeslurp", "E", 1213694223, "slurpeeslurp", "E", 1213694228, "slurpeeslurp", "E", 1213694249, "slurpeeslurp", "E", 1213694280, "slurpeeslurp", "E", 1213694283, "slurpeeslurp", "E", 1213694312, "slurpeeslurp", "E", 1213694326, "slurpeeslurp", "E", 1213694371, "slurpeeslurp", "K", 1213694430, "slurpeeslurp", "E", 1213694433, "slurpeeslurp", "E", 1213694435, "slurpeeslurp", "E", 1213694846, "slurpeeslurp", "E", 1213694858, "slurpeeslurp", "E", 1218892123, "slurpeeslurp", "E", 1218892144, "slurpeeslurp", "K", 1218892159, "slurpeeslurp", "R", 1218892305, "slurpeeslurp", "E", 1218892757, "slurpeeslurp", "E", 1218894161, "slurpeeslurp", "E", 1218894359, "slurpeeslurp", "E", 1218895191, "slurpeeslurp", "E", 1218895216, "slurpeeslurp", "E", 1218895299, "slurpeeslurp", "E", 1451419408, "rorschakovacs", "E", 1460190523, "tonyd", "R", 1565800863, "sendnoodlez", "E", 1565800917, "sendnoodlez", "X" \})
      </Core:Property>
      <Core:Property property="skill:fatigue">100.0</Core:Property>
      <Core:Property property="volition">0</Core:Property>
      <Core:Property property="writable">"1"</Core:Property>
    </Core:Properties>
    <Notes:Notes>
      <Notes:Category cat="QA" catstate="Open">
        <Notes:Note ix="966637404" state="Open" user="michaelb">
           The basic, original scroll.
        </Notes:Note>
      </Notes:Category>
    </Notes:Notes>
  </Base:Thing>
</object>
